sqlalchemy_enum_list.py
SQLAlchemy_Enum_List-0.1.1.dist-info/DESCRIPTION.rst
SQLAlchemy_Enum_List-0.1.1.dist-info/METADATA
SQLAlchemy_Enum_List-0.1.1.dist-info/metadata.json
SQLAlchemy_Enum_List-0.1.1.dist-info/RECORD
SQLAlchemy_Enum_List-0.1.1.dist-info/top_level.txt
SQLAlchemy_Enum_List-0.1.1.dist-info/WHEEL
