Metadata-Version: 2.0
Name: SQLAlchemy-Enum-List
Version: 0.1.1
Summary: Store list of enum member.
Home-page: https://github.com/spoqa/sqlalchemy-enum-list
Author: Kang Hyojun
Author-email: iam.kanghyojun@gmail.com
License: MIT License
Platform: UNKNOWN
Classifier: Development Status :: 4 - Beta
Classifier: Intended Audience :: Developers
Classifier: License :: OSI Approved :: MIT License
Classifier: Operating System :: OS Independent
Classifier: Programming Language :: Python :: 2.7
Classifier: Programming Language :: Python :: 3.2
Classifier: Programming Language :: Python :: 3.3
Classifier: Programming Language :: Python :: 3.4
Classifier: Programming Language :: Python :: 3.5
Classifier: Programming Language :: Python :: Implementation :: CPython
Classifier: Programming Language :: Python :: Implementation :: PyPy
Classifier: Programming Language :: SQL
Classifier: Topic :: Database :: Front-Ends
Classifier: Topic :: Software Development
Requires-Dist: six
Requires-Dist: SQLAlchemy (>=0.8.0)
Requires-Dist: enum34 (>=1.1.6); python_version<'3.5'
Provides-Extra: tests
Requires-Dist: tox; extra == 'tests'
Requires-Dist: pytest; extra == 'tests'
